hito_tools/ad.py
hito_tools/agents.py
hito_tools/core.py
hito_tools/exceptions.py
hito_tools/nsip.py
hito_tools/projects.py
hito_tools/teams.py
hito_tools/utils.py
hito_tools-24.8.1.dist-info/LICENSE
hito_tools-24.8.1.dist-info/METADATA
hito_tools-24.8.1.dist-info/WHEEL
hito_tools-24.8.1.dist-info/RECORD
