Metadata-Version: 2.1
Name: hito-tools
Version: 24.8.1
Summary: Modules for interacting with Hito and NSIP
Author: Michel Jouvin
Author-email: michel.jouvin@ijclab.in2p3.fr
Requires-Python: >=3.8,<4.0
Classifier: Programming Language :: Python :: 3
Classifier: Programming Language :: Python :: 3.8
Classifier: Programming Language :: Python :: 3.9
Classifier: Programming Language :: Python :: 3.10
Classifier: Programming Language :: Python :: 3.11
Requires-Dist: pandas (>=2.2)
Requires-Dist: requests (>=2.28,<3.0)
